chaster/__init__.py
chaster/api.py
chaster/conversation.py
chaster/extensions.py
chaster/lock.py
chaster/setup.py
chaster/triggers.py
chaster/user.py
chaster/util.py
chaster_sdk-0.1.7.dist-info/LICENSE
chaster_sdk-0.1.7.dist-info/METADATA
chaster_sdk-0.1.7.dist-info/WHEEL
chaster_sdk-0.1.7.dist-info/top_level.txt
chaster_sdk-0.1.7.dist-info/RECORD
