Metadata-Version: 2.1
Name: chaster-sdk
Version: 0.1.7
Summary: Chaster python sdk
Author-email: Poofy <poofy.enigma@gmail.com>
Project-URL: Homepage, https://github.com/PoofyEnigma/chaster-python-sdk
Project-URL: Issues, https://github.com/PoofyEnigma/chaster-python-sdk/issues
Classifier: Programming Language :: Python :: 3
Classifier: License :: OSI Approved :: Apache Software License
Classifier: Operating System :: OS Independent
Requires-Python: >=3.8
License-File: LICENSE
Requires-Dist: python-dateutil
Requires-Dist: requests
